odoo/addons/account_payment_notification/README.rst
odoo/addons/account_payment_notification/__init__.py
odoo/addons/account_payment_notification/__manifest__.py
odoo/addons/account_payment_notification/data/mail_template.xml
odoo/addons/account_payment_notification/data/sms_template.xml
odoo/addons/account_payment_notification/i18n/account_payment_notification.pot
odoo/addons/account_payment_notification/i18n/es.po
odoo/addons/account_payment_notification/i18n/it.po
odoo/addons/account_payment_notification/models/__init__.py
odoo/addons/account_payment_notification/models/account_payment.py
odoo/addons/account_payment_notification/models/res_company.py
odoo/addons/account_payment_notification/readme/CONFIGURE.md
odoo/addons/account_payment_notification/readme/CONTRIBUTORS.md
odoo/addons/account_payment_notification/readme/DESCRIPTION.md
odoo/addons/account_payment_notification/readme/ROADMAP.md
odoo/addons/account_payment_notification/readme/USAGE.md
odoo/addons/account_payment_notification/security/sms_template.xml
odoo/addons/account_payment_notification/static/description/icon.png
odoo/addons/account_payment_notification/static/description/index.html
odoo/addons/account_payment_notification/tests/__init__.py
odoo/addons/account_payment_notification/tests/test_notifications.py
odoo/addons/account_payment_notification/views/account_payment_views.xml
odoo/addons/account_payment_notification/wizards/__init__.py
odoo/addons/account_payment_notification/wizards/res_config_settings.py
odoo/addons/account_payment_notification/wizards/res_config_settings_views.xml
odoo_addon_account_payment_notification-18.0.1.0.1.dist-info/METADATA
odoo_addon_account_payment_notification-18.0.1.0.1.dist-info/WHEEL
odoo_addon_account_payment_notification-18.0.1.0.1.dist-info/top_level.txt
odoo_addon_account_payment_notification-18.0.1.0.1.dist-info/RECORD
